{
  "projects": [
   
    {
      "name": "Pokemon Cards",
      "key": "pokemon-project",
      "tags": ["HTML", "CSS", "REACT"],
      "links": {
        "live": "https://pokemon-project-vd.herokuapp.com/",
        "github": "https://github.com/Vaasu-Dhand/Pokemon-Project"
      },
      "description": "A fun website that displays Pokemon Cards from all generations. Used custom CSS for beautiful UI and animations. Implemented concepts like - Infinite Scroll, PreLoad Screen, Card Flip, etc"
    }
  ]
}
